satsuki/__init__.py
satsuki/cli.py
satsuki/logging.conf
satsuki-0.1.85.dist-info/licenses/LICENSE
satsuki-0.1.85.dist-info/METADATA
satsuki-0.1.85.dist-info/WHEEL
satsuki-0.1.85.dist-info/entry_points.txt
satsuki-0.1.85.dist-info/top_level.txt
satsuki-0.1.85.dist-info/RECORD
