Metadata-Version: 2.4
Name: satsuki
Version: 0.1.85
Summary: Manage GitHub releases and release assets.
Home-page: https://github.com/plus3it/satsuki
Author: Plus3 IT Solutions, LLC
Author-email: projects@plus3it.com
License: Apache Software License 2.0
Platform: Linux
Platform: Windows
Platform: Darwin
Platform: MacOS
Classifier: Development Status :: 4 - Beta
Classifier: Intended Audience :: Developers
Classifier: Operating System :: MacOS :: MacOS X
Classifier: Operating System :: POSIX :: Linux
Classifier: Operating System :: Microsoft :: Windows
Classifier: Programming Language :: Python
Classifier: Programming Language :: Python :: 3
Classifier: Programming Language :: Python :: 3.12
Classifier: Programming Language :: Python :: Implementation :: CPython
Classifier: Programming Language :: Python :: Implementation :: PyPy
Classifier: Topic :: Utilities
License-File: LICENSE
Requires-Dist: click
Requires-Dist: PyGithub
Dynamic: license-file
